data_preparation/cropping.py
data_preparation/threed_pointcloud.py
test/__init__.py
pointcloud_extraction_toolkit-0.0.3.dist-info/LICENSE
pointcloud_extraction_toolkit-0.0.3.dist-info/METADATA
pointcloud_extraction_toolkit-0.0.3.dist-info/WHEEL
pointcloud_extraction_toolkit-0.0.3.dist-info/top_level.txt
pointcloud_extraction_toolkit-0.0.3.dist-info/RECORD
