Metadata-Version: 2.1
Name: pointcloud_extraction_toolkit
Version: 0.0.3
Summary: scripts for allowing user to load and preprocess data from the lidar / image data in order to convert into raw attributed point cloud dataset
Author: Dhruv Malik
Author-email: dhruv@extralabs.xyz
Classifier: Programming Language :: Python :: 3
Classifier: License :: OSI Approved :: MIT License
Classifier: Operating System :: OS Independent
Requires-Python: >=3.8
License-File: LICENSE
